algojig/__init__.py
algojig/algojig
algojig/check.py
algojig/dryrun.py
algojig/exceptions.py
algojig/gojig.py
algojig/ledger.py
algojig/program.py
algojig/teal.py
algojig/tealish.py
algojig-0.0.2.dist-info/LICENSE
algojig-0.0.2.dist-info/METADATA
algojig-0.0.2.dist-info/WHEEL
algojig-0.0.2.dist-info/top_level.txt
algojig-0.0.2.dist-info/RECORD
